Metadata-Version: 1.0
Name: azure-synapse-ml-predict
Version: 1.0.0
Summary: Ethical research - dep confusion package. This is not a real package, do not install.
Home-page: UNKNOWN
Author: UNKNOWN
Author-email: UNKNOWN
License: UNKNOWN
Platform: UNKNOWN
